setup.cfg
setup.py
optimizely/__init__.py
optimizely/client.py
optimizely/error.py
optimizely/resource.py
optimizely.egg-info/PKG-INFO
optimizely.egg-info/SOURCES.txt
optimizely.egg-info/dependency_links.txt
optimizely.egg-info/not-zip-safe
optimizely.egg-info/requires.txt
optimizely.egg-info/top_level.txt