Metadata-Version: 1.1
Name: optimizely
Version: 0.5
Summary: A Python interface to Optimizely's REST API.
Home-page: https://github.com/optimizely/optimizely-client-python
Author: Optimizely
Author-email: developers@optimizely.com
License: UNKNOWN
Download-URL: https://github.com/optimizely/optimizely-client-python/tarball/0.5
Keywords: python-sdk,optimizely
Platform: UNKNOWN
